redtape/__init__.py
redtape/__main__.py
redtape/__version__.py
redtape/admin.py
redtape/cli.py
redtape/connectors.py
redtape/relation_tuple.py
redtape/specification/__init__.py
redtape/specification/models.py
redtape_py-0.4.2.dist-info/LICENSE
redtape_py-0.4.2.dist-info/METADATA
redtape_py-0.4.2.dist-info/WHEEL
redtape_py-0.4.2.dist-info/entry_points.txt
redtape_py-0.4.2.dist-info/RECORD
