Metadata-Version: 2.1
Name: redtape-py
Version: 0.4.2
Summary: A permission management tool for AWS Redshift.
License: MIT
Keywords: redshift,database,privileges
Author: Tomás Farías Santana
Author-email: tomas@tomasfarias.dev
Requires-Python: >=3.10,<4.0
Classifier: Development Status :: 3 - Alpha
Classifier: Intended Audience :: System Administrators
Classifier: License :: OSI Approved :: MIT License
Classifier: Programming Language :: Python :: 3
Classifier: Programming Language :: Python :: 3.10
Classifier: Programming Language :: Python :: 3.11
Classifier: Programming Language :: Python :: 3.12
Classifier: Programming Language :: Python :: 3.8
Classifier: Programming Language :: Python :: 3.9
Classifier: Topic :: Database
Requires-Dist: PyYAML (>=6.0,<7.0)
Requires-Dist: aenum (>=3.1,<4.0)
Requires-Dist: attrs (>=23.2,<24.0)
Requires-Dist: cattrs (>=23.2,<24.0)
Requires-Dist: environ-config (>=23.2,<24.0)
Requires-Dist: psycopg2-binary (>=2.9.3,<3.0.0)
Requires-Dist: rich (>=13.7,<14.0)
Requires-Dist: typer (>=0.9,<0.10)
